coroutines.py
coroutines-0.2.0.dist-info/METADATA
coroutines-0.2.0.dist-info/WHEEL
coroutines-0.2.0.dist-info/licenses/LICENSE
coroutines-0.2.0.dist-info/RECORD
