Metadata-Version: 2.1
Name: coroutines
Version: 0.2.0
Summary: Coroutines without an event loop
Project-URL: Homepage, https://github.com/ntessore/coroutines
Project-URL: Issues, https://github.com/ntessore/coroutines/issues
Author-email: Nicolas Tessore <n.tessore@ucl.ac.uk>
License-Expression: MIT
License-File: LICENSE
Classifier: License :: OSI Approved :: MIT License
Classifier: Operating System :: OS Independent
Classifier: Programming Language :: Python :: 3
Requires-Python: >=3.7
Provides-Extra: test
Requires-Dist: pytest>=6.0; extra == 'test'
